<?xml version="1.0" encoding="UTF-8"?>
<settings xmlns="http://maven.apache.org/SETTINGS/1.0.0"
		  xmlns:xsi="http://www.w3.org/2001/XMLSchema-instance"
		  xsi:schemaLocation="http://maven.apache.org/SETTINGS/1.0.0
                          https://maven.apache.org/xsd/settings-1.0.0.xsd">

	<profiles>
		<profile>
			<id>spring-community</id>
			<activation>
				<activeByDefault>true</activeByDefault>
			</activation>
			<repositories>
				<repository>
					<id>spring-snapshots</id>
					<name>Spring Snapshots</name>
					<url>https://repo.spring.io/snapshot</url>
					<snapshots>
						<enabled>true</enabled>
					</snapshots>
				</repository>
				<repository>
					<id>spring-milestones</id>
					<name>Spring Milestones</name>
					<url>https://repo.spring.io/milestone</url>
					<snapshots>
						<enabled>false</enabled>
					</snapshots>
				</repository>
			</repositories>
			<pluginRepositories>
				<pluginRepository>
					<id>spring-snapshots</id>
					<name>Spring Snapshots</name>
					<url>https://repo.spring.io/snapshot</url>
					<snapshots>
						<enabled>true</enabled>
					</snapshots>
				</pluginRepository>
			</pluginRepositories>
		</profile>
	</profiles>

	<activeProfiles>
		<activeProfile>spring-community</activeProfile>
	</activeProfiles>
</settings>